etu_fastapi_frame/__init__.py
etu_fastapi_frame/main.py
etu_fastapi_frame/fastapi/0.95.2/cfg/.gitignore
etu_fastapi_frame/fastapi/0.95.2/cfg/Dockerfile
etu_fastapi_frame/fastapi/0.95.2/cfg/README.md
etu_fastapi_frame/fastapi/0.95.2/cfg/fastapi-all.txt
etu_fastapi_frame/fastapi/0.95.2/cfg/requirements.txt
etu_fastapi_frame/fastapi/0.95.2/cfg/app/__init__.py
etu_fastapi_frame/fastapi/0.95.2/cfg/app/initial_data.py
etu_fastapi_frame/fastapi/0.95.2/cfg/app/main.py
etu_fastapi_frame/fastapi/0.95.2/cfg/app/routers.py
etu_fastapi_frame/fastapi/0.95.2/cfg/app/api/__init__.py
etu_fastapi_frame/fastapi/0.95.2/cfg/app/api/deps.py
etu_fastapi_frame/fastapi/0.95.2/cfg/app/api/api_v1/__init__.py
etu_fastapi_frame/fastapi/0.95.2/cfg/app/api/api_v1/api.py
etu_fastapi_frame/fastapi/0.95.2/cfg/app/api/api_v1/endpoints/__init__.py
etu_fastapi_frame/fastapi/0.95.2/cfg/app/api/api_v1/endpoints/demos.py
etu_fastapi_frame/fastapi/0.95.2/cfg/app/api/api_v1/endpoints/health.py
etu_fastapi_frame/fastapi/0.95.2/cfg/app/api/api_v1/endpoints/login.py
etu_fastapi_frame/fastapi/0.95.2/cfg/app/api/api_v1/endpoints/users.py
etu_fastapi_frame/fastapi/0.95.2/cfg/app/core/__init__.py
etu_fastapi_frame/fastapi/0.95.2/cfg/app/core/config.py
etu_fastapi_frame/fastapi/0.95.2/cfg/app/core/log.py
etu_fastapi_frame/fastapi/0.95.2/cfg/app/core/security.py
etu_fastapi_frame/fastapi/0.95.2/cfg/app/core/middleware/__init__.py
etu_fastapi_frame/fastapi/0.95.2/cfg/app/core/middleware/global_authorized.py
etu_fastapi_frame/fastapi/0.95.2/cfg/app/core/middleware/global_request.py
etu_fastapi_frame/fastapi/0.95.2/cfg/app/core/middleware/log_formatter.py
etu_fastapi_frame/fastapi/0.95.2/cfg/app/crud/__init__.py
etu_fastapi_frame/fastapi/0.95.2/cfg/app/crud/base.py
etu_fastapi_frame/fastapi/0.95.2/cfg/app/crud/crud_user.py
etu_fastapi_frame/fastapi/0.95.2/cfg/app/db/__init__.py
etu_fastapi_frame/fastapi/0.95.2/cfg/app/db/base.py
etu_fastapi_frame/fastapi/0.95.2/cfg/app/db/base_class.py
etu_fastapi_frame-1.3.1.dist-info/LICENSE
etu_fastapi_frame-1.3.1.dist-info/METADATA
etu_fastapi_frame-1.3.1.dist-info/WHEEL
etu_fastapi_frame-1.3.1.dist-info/entry_points.txt
etu_fastapi_frame-1.3.1.dist-info/top_level.txt
etu_fastapi_frame-1.3.1.dist-info/zip-safe
etu_fastapi_frame-1.3.1.dist-info/RECORD
